LICENSE
README.md
beancount_swe/__init__.py
beancount_swe/lf.py
beancount_swe-0.1.1.dist-info/LICENSE
beancount_swe-0.1.1.dist-info/WHEEL
beancount_swe-0.1.1.dist-info/METADATA
beancount_swe-0.1.1.dist-info/RECORD
